mcvariable/__init__.py
mcvariable/mcvariable.py
mcvariable-0.1.0.dist-info/AUTHORS
mcvariable-0.1.0.dist-info/LICENSE
mcvariable-0.1.0.dist-info/METADATA
mcvariable-0.1.0.dist-info/WHEEL
mcvariable-0.1.0.dist-info/top_level.txt
mcvariable-0.1.0.dist-info/RECORD
